neuronbridge/__init__.py
neuronbridge/client.py
neuronbridge/generate_schemas.py
neuronbridge/model.py
neuronbridge/utils.py
neuronbridge/validate_ray.py
neuronbridge/validate_worker.py
neuronbridge_python-3.3.0.dist-info/licenses/LICENSE.md
tests/test_model.py
neuronbridge_python-3.3.0.dist-info/METADATA
neuronbridge_python-3.3.0.dist-info/WHEEL
neuronbridge_python-3.3.0.dist-info/top_level.txt
neuronbridge_python-3.3.0.dist-info/RECORD
