Metadata-Version: 2.4
Name: neuronbridge-python
Version: 3.3.0
Summary: Python API for NeuronBridge
Author-email: Konrad Rokicki <rokickik@janelia.hhmi.org>
Project-URL: Homepage, https://github.com/JaneliaSciComp/neuronbridge-python/
Keywords: neuroscience,neuron,similarity,search,api
Classifier: License :: OSI Approved :: BSD License
Classifier: Operating System :: OS Independent
Classifier: Programming Language :: Python :: 3
Classifier: Intended Audience :: Science/Research
Classifier: Topic :: Scientific/Engineering :: Bio-Informatics
Classifier: Topic :: Software Development :: Libraries :: Python Modules
Requires-Python: >=3.9
License-File: LICENSE.md
Requires-Dist: pydantic~=2.9.1
Requires-Dist: python-rapidjson~=1.20
Requires-Dist: ray[default]~=2.39.0
Requires-Dist: memray
Requires-Dist: tqdm
Provides-Extra: notebooks
Requires-Dist: jupyter; extra == "notebooks"
Requires-Dist: ipython-sql; extra == "notebooks"
Requires-Dist: pandas; extra == "notebooks"
Requires-Dist: pillow; extra == "notebooks"
Requires-Dist: blend-modes; extra == "notebooks"
Provides-Extra: test
Requires-Dist: pytest~=7.1.3; extra == "test"
Requires-Dist: coverage; extra == "test"
Provides-Extra: release
Requires-Dist: build; extra == "release"
Requires-Dist: twine; extra == "release"
Dynamic: license-file
